pgmini_migrate/__init__.py
pgmini_migrate/__main__.py
pgmini_migrate/cli.py
pgmini_migrate/utils.py
pgmini_migrate-0.1.3.dist-info/licenses/LICENSE
pgmini_migrate-0.1.3.dist-info/METADATA
pgmini_migrate-0.1.3.dist-info/WHEEL
pgmini_migrate-0.1.3.dist-info/entry_points.txt
pgmini_migrate-0.1.3.dist-info/top_level.txt
pgmini_migrate-0.1.3.dist-info/RECORD
