Metadata-Version: 2.4
Name: pgmini-migrate
Version: 0.1.3
Summary: A minimal PostgreSQL migration tool for Python
Author-email: Nguyen Vu Duy Luan <nvdluan@gmail.com>
License: Copyright (c) 2025 Nguyen Vu Duy Luan
Project-URL: Homepage, https://github.com/NVDLuan/pgmini-migrate
Project-URL: Issues, https://github.com/NVDLuan/pgmini-migrate/issues
Requires-Python: >=3.10
License-File: LICENSE
Requires-Dist: psycopg[binary]>=3.1.8
Requires-Dist: dotenv<0.10.0,>=0.9.9
Requires-Dist: click<9.0.0,>=8.2.1
Dynamic: license-file
